{"data":{"ID":"bw3-8","Name":"Karrablast","Supertype":"Pokémon","Subtypes":["Basic"],"HP":"60","Types":["Grass"],"EvolvesFrom":"","Rules":null,"Attacks":[{"Name":"Mysterious Evolution","Cost":["Colorless"],"ConvertedEnergyCost":1,"Damage":"","Text":"If Shelmet is in play, search your deck for a card that evolves from this Pokémon and put it onto this Pokémon. (This counts as evolving this Pokémon.) Shuffle your deck afterward."},{"Name":"Fury Attack","Cost":["Colorless","Colorless"],"ConvertedEnergyCost":2,"Damage":"10×","Text":"Flip 3 coins. This attack does 10 damage times the number of heads."}],"Weaknesses":[{"Type":"Fire","Value":"×2"}],"RetreatCost":["Colorless"],"ConvertedRetreatCost":1,"Set":{"ID":"bw3","Name":"Noble Victories","Series":"Black \u0026 White","PrintedTotal":101,"Total":102,"Legalities":{"expanded":"Legal","unlimited":"Legal"},"PtcgoCode":"NVI","ReleaseDate":"2011/11/16","UpdatedAt":"2018/03/04 10:35:00","Images":{"logo":"https://images.pokemontcg.io/bw3/logo.png","symbol":"https://images.pokemontcg.io/bw3/symbol.png"}},"Number":"8","Artist":"sui","Rarity":"Common","NationalPokedexNumbers":[588],"Legalities":{"expanded":"Legal","unlimited":"Legal"},"RegulationMark":"","Images":{"large":"https://images.pokemontcg.io/bw3/8_hires.png","small":"https://images.pokemontcg.io/bw3/8.png"},"CardMarket":{"URL":"https://prices.pokemontcg.io/cardmarket/bw3-8","UpdatedAt":"2022/03/10","Prices":{"AverageSellPrice":0.97,"LowPrice":0.75,"TrendPrice":2.12,"ReverseHoloTrend":1.48,"Avg1":0.95,"Avg7":3.87,"Avg30":2.51,"ReverseHoloAvg1":1,"ReverseHoloAvg7":1.22,"ReverseHoloAvg30":2}}}}
