{"data":{"ID":"dp5-85","Name":"Poké Ball","Supertype":"Trainer","Subtypes":["Item"],"HP":"","Types":null,"EvolvesFrom":"","Rules":["Flip a coin. If heads, search your deck for a Pokémon, show it to your opponent, and put it into your hand. Shuffle your deck afterward."],"Attacks":null,"Weaknesses":null,"RetreatCost":null,"ConvertedRetreatCost":0,"Set":{"ID":"dp5","Name":"Majestic Dawn","Series":"Diamond \u0026 Pearl","PrintedTotal":100,"Total":100,"Legalities":{"unlimited":"Legal"},"PtcgoCode":"MD","ReleaseDate":"2008/05/01","UpdatedAt":"2018/03/04 10:35:00","Images":{"logo":"https://images.pokemontcg.io/dp5/logo.png","symbol":"https://images.pokemontcg.io/dp5/symbol.png"}},"Number":"85","Artist":"Ryo Ueda","Rarity":"Uncommon","NationalPokedexNumbers":null,"Legalities":{"expanded":"Legal","standard":"Legal","unlimited":"Legal"},"RegulationMark":"","Images":{"large":"https://images.pokemontcg.io/dp5/85_hires.png","small":"https://images.pokemontcg.io/dp5/85.png"},"CardMarket":{"URL":"https://prices.pokemontcg.io/cardmarket/dp5-85","UpdatedAt":"2022/03/18","Prices":{"AverageSellPrice":0.04,"LowPrice":0.02,"TrendPrice":0.19,"ReverseHoloTrend":0.76,"Avg1":0.04,"Avg7":0.15,"Avg30":0.25,"ReverseHoloAvg1":1.49,"ReverseHoloAvg7":0.66,"ReverseHoloAvg30":0.61}}}}
