{"data":{"ID":"dp7-86","Name":"Luxury Ball","Supertype":"Trainer","Subtypes":["Item"],"HP":"","Types":null,"EvolvesFrom":"","Rules":["Search your deck for a Pokémon (excluding Pokémon LV.X), show it to your opponent, and put it into your hand. Shuffle your deck afterward. If any Luxury Ball is in your discard pile, you can't play this card."],"Attacks":null,"Weaknesses":null,"RetreatCost":null,"ConvertedRetreatCost":0,"Set":{"ID":"dp7","Name":"Stormfront","Series":"Diamond \u0026 Pearl","PrintedTotal":100,"Total":106,"Legalities":{"unlimited":"Legal"},"PtcgoCode":"SF","ReleaseDate":"2008/11/01","UpdatedAt":"2020/05/01 16:06:00","Images":{"logo":"https://images.pokemontcg.io/dp7/logo.png","symbol":"https://images.pokemontcg.io/dp7/symbol.png"}},"Number":"86","Artist":"Ryo Ueda","Rarity":"Uncommon","NationalPokedexNumbers":null,"Legalities":{"unlimited":"Legal"},"RegulationMark":"","Images":{"large":"https://images.pokemontcg.io/dp7/86_hires.png","small":"https://images.pokemontcg.io/dp7/86.png"},"CardMarket":{"URL":"https://prices.pokemontcg.io/cardmarket/dp7-86","UpdatedAt":"2022/03/14","Prices":{"AverageSellPrice":0.14,"LowPrice":0.02,"TrendPrice":0.21,"ReverseHoloTrend":1.58,"Avg1":0.15,"Avg7":0.14,"Avg30":0.22,"ReverseHoloAvg1":1.99,"ReverseHoloAvg7":1.73,"ReverseHoloAvg30":1.41}}}}
