{"data":{"ID":"ex12-89","Name":"Walrein ex","Supertype":"Pokémon","Subtypes":["Basic","EX"],"HP":"150","Types":["Water"],"EvolvesFrom":"Sealeo","Rules":["When Pokémon-ex has been Knocked Out, your opponent takes 2 Prize cards."],"Attacks":[{"Name":"Water Arrow","Cost":["Water","Colorless"],"ConvertedEnergyCost":2,"Damage":"","Text":"Choose 1 of your opponent's Pokémon. This attack does 40 damage to that Pokémon. (Don't apply Weakness and Resistance for Benched Pokémon.)"},{"Name":"Ice Throw","Cost":["Water","Water","Colorless","Colorless"],"ConvertedEnergyCost":4,"Damage":"80","Text":"If the Defending Pokémon is a Fighting Pokémon, this attack's base damage is 120 instead of 80."}],"Weaknesses":[{"Type":"Fighting","Value":"×2"},{"Type":"Metal","Value":"×2"}],"RetreatCost":["Colorless","Colorless","Colorless"],"ConvertedRetreatCost":3,"Set":{"ID":"ex12","Name":"Legend Maker","Series":"EX","PrintedTotal":92,"Total":93,"Legalities":{"unlimited":"Legal"},"PtcgoCode":"LM","ReleaseDate":"2006/02/01","UpdatedAt":"2018/03/04 10:35:00","Images":{"logo":"https://images.pokemontcg.io/ex12/logo.png","symbol":"https://images.pokemontcg.io/ex12/symbol.png"}},"Number":"89","Artist":"Kimiya Masago","Rarity":"Rare Holo EX","NationalPokedexNumbers":[365],"Legalities":{"unlimited":"Legal"},"RegulationMark":"","Images":{"large":"https://images.pokemontcg.io/ex12/89_hires.png","small":"https://images.pokemontcg.io/ex12/89.png"},"CardMarket":{"URL":"https://prices.pokemontcg.io/cardmarket/ex12-89","UpdatedAt":"2022/03/14","Prices":{"AverageSellPrice":17,"LowPrice":3.9,"TrendPrice":15.86,"ReverseHoloTrend":19.25,"Avg1":7,"Avg7":13.48,"Avg30":14,"ReverseHoloAvg1":45,"ReverseHoloAvg7":17.94,"ReverseHoloAvg30":12.37}}}}
