{"data":{"ID":"ex3-3","Name":"Crawdaunt","Supertype":"Pokémon","Subtypes":["Stage 1"],"HP":"80","Types":["Water"],"EvolvesFrom":"Corphish","Rules":null,"Attacks":[{"Name":"Guillotine","Cost":["Water","Colorless","Colorless"],"ConvertedEnergyCost":3,"Damage":"50","Text":""}],"Weaknesses":[{"Type":"Lightning","Value":"×2"}],"RetreatCost":["Colorless","Colorless"],"ConvertedRetreatCost":2,"Set":{"ID":"ex3","Name":"Dragon","Series":"EX","PrintedTotal":97,"Total":100,"Legalities":{"unlimited":"Legal"},"PtcgoCode":"DR","ReleaseDate":"2003/09/18","UpdatedAt":"2019/01/28 16:44:00","Images":{"logo":"https://images.pokemontcg.io/ex3/logo.png","symbol":"https://images.pokemontcg.io/ex3/symbol.png"}},"Number":"3","Artist":"Hisao Nakamura","Rarity":"Rare Holo","NationalPokedexNumbers":[342],"Legalities":{"unlimited":"Legal"},"RegulationMark":"","Images":{"large":"https://images.pokemontcg.io/ex3/3_hires.png","small":"https://images.pokemontcg.io/ex3/3.png"},"CardMarket":{"URL":"https://prices.pokemontcg.io/cardmarket/ex3-3","UpdatedAt":"2022/03/18","Prices":{"AverageSellPrice":1.77,"LowPrice":0.18,"TrendPrice":0.95,"ReverseHoloTrend":2.78,"Avg1":0.94,"Avg7":1.61,"Avg30":2.14,"ReverseHoloAvg1":4,"ReverseHoloAvg7":2.65,"ReverseHoloAvg30":2.27}}}}
