{"data":{"ID":"ex3-14","Name":"Dragonair","Supertype":"Pokémon","Subtypes":["Stage 1"],"HP":"70","Types":["Colorless"],"EvolvesFrom":"Dratini","Rules":null,"Attacks":[{"Name":"Dazzle Blast","Cost":["Lightning","Colorless"],"ConvertedEnergyCost":2,"Damage":"20","Text":"Flip a coin. If heads, the Defending Pokémon is now Confused."},{"Name":"Healing Wave","Cost":["Water","Colorless","Colorless"],"ConvertedEnergyCost":3,"Damage":"30","Text":"Remove 1 damage counter from each of your Active Pokémon."}],"Weaknesses":[{"Type":"Colorless","Value":"×2"}],"RetreatCost":["Colorless","Colorless"],"ConvertedRetreatCost":2,"Set":{"ID":"ex3","Name":"Dragon","Series":"EX","PrintedTotal":97,"Total":100,"Legalities":{"unlimited":"Legal"},"PtcgoCode":"DR","ReleaseDate":"2003/09/18","UpdatedAt":"2019/01/28 16:44:00","Images":{"logo":"https://images.pokemontcg.io/ex3/logo.png","symbol":"https://images.pokemontcg.io/ex3/symbol.png"}},"Number":"14","Artist":"Aya Kusube","Rarity":"Rare","NationalPokedexNumbers":[148],"Legalities":{"unlimited":"Legal"},"RegulationMark":"","Images":{"large":"https://images.pokemontcg.io/ex3/14_hires.png","small":"https://images.pokemontcg.io/ex3/14.png"},"CardMarket":{"URL":"https://prices.pokemontcg.io/cardmarket/ex3-14","UpdatedAt":"2022/03/10","Prices":{"AverageSellPrice":1.5,"LowPrice":0.05,"TrendPrice":1.61,"ReverseHoloTrend":8.79,"Avg1":0.5,"Avg7":1.85,"Avg30":0.87,"ReverseHoloAvg1":4,"ReverseHoloAvg7":7.19,"ReverseHoloAvg30":5.25}}}}
