{"data":{"ID":"ex8-86","Name":"Energy Charge","Supertype":"Trainer","Subtypes":null,"HP":"","Types":null,"EvolvesFrom":"","Rules":["Flip a coin. If heads, search your discard pile for 2 Energy cards (1 if there is only 1), show them to your opponent, and shuffle them into your deck."],"Attacks":null,"Weaknesses":null,"RetreatCost":null,"ConvertedRetreatCost":0,"Set":{"ID":"ex8","Name":"Deoxys","Series":"EX","PrintedTotal":107,"Total":108,"Legalities":{"unlimited":"Legal"},"PtcgoCode":"DX","ReleaseDate":"2005/02/01","UpdatedAt":"2019/01/28 16:44:00","Images":{"logo":"https://images.pokemontcg.io/ex8/logo.png","symbol":"https://images.pokemontcg.io/ex8/symbol.png"}},"Number":"86","Artist":"Keiji Kinebuchi","Rarity":"Uncommon","NationalPokedexNumbers":null,"Legalities":{"unlimited":"Legal"},"RegulationMark":"","Images":{"large":"https://images.pokemontcg.io/ex8/86_hires.png","small":"https://images.pokemontcg.io/ex8/86.png"},"CardMarket":{"URL":"https://prices.pokemontcg.io/cardmarket/ex8-86","UpdatedAt":"2022/03/14","Prices":{"AverageSellPrice":0.67,"LowPrice":0.1,"TrendPrice":0.79,"ReverseHoloTrend":1.71,"Avg1":0.5,"Avg7":0.81,"Avg30":0.66,"ReverseHoloAvg1":2.99,"ReverseHoloAvg7":1.5,"ReverseHoloAvg30":1.88}}}}
