{"data":{"ID":"mcd15-11","Name":"Zigzagoon","Supertype":"Pokémon","Subtypes":["Basic"],"HP":"60","Types":["Colorless"],"EvolvesFrom":"","Rules":null,"Attacks":[{"Name":"Sand Attack","Cost":["Colorless"],"ConvertedEnergyCost":1,"Damage":"","Text":"If the Defending Pokémon tries to attack during your opponent's next turn, your opponent flips a coin. If tails, that attack does nothing."},{"Name":"Headbutt","Cost":["Colorless","Colorless"],"ConvertedEnergyCost":2,"Damage":"20","Text":""}],"Weaknesses":[{"Type":"Fighting","Value":"×2"}],"RetreatCost":["Colorless"],"ConvertedRetreatCost":1,"Series":"","PrintedTotal":0,"Total":0,"PtcgoCode":"","ReleaseDate":"","UpdatedAt":"","Number":"11","Artist":"Sumiyoshi Kizuki","Rarity":"Promo","NationalPokedexNumbers":[263],"Legalities":{"expanded":"Legal","unlimited":"Legal"},"RegulationMark":"","Images":{"large":"https://images.pokemontcg.io/mcd15/11_hires.png","small":"https://images.pokemontcg.io/mcd15/11.png"}}}
