{"data":{"ID":"mcd21-1","Name":"Bulbasaur","Supertype":"Pokémon","Subtypes":["Basic"],"HP":"70","Types":["Grass"],"EvolvesFrom":"","Rules":null,"Attacks":[{"Name":"Razor Leaf","Cost":["Grass","Colorless"],"ConvertedEnergyCost":2,"Damage":"30","Text":""}],"Weaknesses":[{"Type":"Fire","Value":"×2"}],"RetreatCost":["Colorless","Colorless"],"ConvertedRetreatCost":2,"Set":{"ID":"mcd21","Name":"McDonald's Collection 2021","Series":"Other","PrintedTotal":25,"Total":25,"Legalities":{"expanded":"Legal","unlimited":"Legal"},"PtcgoCode":"","ReleaseDate":"2021/02/09","UpdatedAt":"2021/09/07 13:00:00","Images":{"logo":"https://images.pokemontcg.io/mcd21/logo.png","symbol":"https://images.pokemontcg.io/mcd21/symbol.png"}},"Number":"1","Artist":"Mizue","Rarity":"Promo","NationalPokedexNumbers":[1],"Legalities":{"expanded":"Legal","unlimited":"Legal"},"RegulationMark":"","Images":{"large":"https://images.pokemontcg.io/mcd21/1_hires.png","small":"https://images.pokemontcg.io/mcd21/1.png"},"CardMarket":{"URL":"https://prices.pokemontcg.io/cardmarket/mcd21-1","UpdatedAt":"2022/03/14","Prices":{"AverageSellPrice":0.19,"LowPrice":0.02,"TrendPrice":0.3,"ReverseHoloTrend":7.4,"Avg1":0.05,"Avg7":0.19,"Avg30":0.19,"ReverseHoloAvg1":10,"ReverseHoloAvg7":9.51,"ReverseHoloAvg30":8.89}}}}
