{"data":{"ID":"pl2-114","Name":"Surfing Pikachu","Supertype":"Pokémon","Subtypes":["Basic"],"HP":"50","Types":["Lightning"],"EvolvesFrom":"","Rules":null,"Attacks":[{"Name":"Surf","Cost":["Water","Water"],"ConvertedEnergyCost":2,"Damage":"30","Text":""}],"Weaknesses":[{"Type":"Fighting","Value":"×2"}],"RetreatCost":["Colorless"],"ConvertedRetreatCost":1,"Set":{"ID":"pl2","Name":"Rising Rivals","Series":"Platinum","PrintedTotal":111,"Total":120,"Legalities":{"unlimited":"Legal"},"PtcgoCode":"RR","ReleaseDate":"2009/05/16","UpdatedAt":"2020/08/14 09:35:00","Images":{"logo":"https://images.pokemontcg.io/pl2/logo.png","symbol":"https://images.pokemontcg.io/pl2/symbol.png"}},"Number":"114","Artist":"Toshinao Aoki","Rarity":"Rare Secret","NationalPokedexNumbers":[25],"Legalities":{"expanded":"Legal","unlimited":"Legal"},"RegulationMark":"","Images":{"large":"https://images.pokemontcg.io/pl2/114_hires.png","small":"https://images.pokemontcg.io/pl2/114.png"},"CardMarket":{"URL":"https://prices.pokemontcg.io/cardmarket/pl2-114","UpdatedAt":"2022/03/14","Prices":{"AverageSellPrice":70,"LowPrice":4,"TrendPrice":25.7,"ReverseHoloTrend":16.04,"Avg1":70,"Avg7":20.62,"Avg30":19.89,"ReverseHoloAvg1":19.99,"ReverseHoloAvg7":11.54,"ReverseHoloAvg30":9.99}}}}
