{"data":{"ID":"pl4-86","Name":"Energy Restore","Supertype":"Trainer","Subtypes":["Item"],"HP":"","Types":null,"EvolvesFrom":"","Rules":["Flip 3 coins. For each heads, put a basic Energy card from your discard pile into your hand. If you don't have that many basic Energy cards in your discard pile, put all of them into your hand."],"Attacks":null,"Weaknesses":null,"RetreatCost":null,"ConvertedRetreatCost":0,"Set":{"ID":"pl4","Name":"Arceus","Series":"Platinum","PrintedTotal":99,"Total":111,"Legalities":{"unlimited":"Legal"},"PtcgoCode":"AR","ReleaseDate":"2009/11/04","UpdatedAt":"2021/07/15 11:30:00","Images":{"logo":"https://images.pokemontcg.io/pl4/logo.png","symbol":"https://images.pokemontcg.io/pl4/symbol.png"}},"Number":"86","Artist":"Ryo Ueda","Rarity":"Uncommon","NationalPokedexNumbers":null,"Legalities":{"unlimited":"Legal"},"RegulationMark":"","Images":{"large":"https://images.pokemontcg.io/pl4/86_hires.png","small":"https://images.pokemontcg.io/pl4/86.png"},"CardMarket":{"URL":"https://prices.pokemontcg.io/cardmarket/pl4-86","UpdatedAt":"2022/03/14","Prices":{"AverageSellPrice":0.05,"LowPrice":0.02,"TrendPrice":0.12,"ReverseHoloTrend":0.51,"Avg1":0.1,"Avg7":0.08,"Avg30":0.13,"ReverseHoloAvg1":0.55,"ReverseHoloAvg7":0.45,"ReverseHoloAvg30":0.37}}}}
