{"data":{"ID":"pop1-3","Name":"Rayquaza","Supertype":"Pokémon","Subtypes":["Basic"],"HP":"80","Types":["Colorless"],"EvolvesFrom":"","Rules":null,"Attacks":[{"Name":"Fly","Cost":["Colorless"],"ConvertedEnergyCost":1,"Damage":"10","Text":"Flip a coin. If tails, this attack does nothing. If heads, prevent all effects of an attack, including damage, done to Rayquaza during your opponent's next turn."},{"Name":"Dragon Claw","Cost":["Fire","Lightning"],"ConvertedEnergyCost":2,"Damage":"30","Text":""}],"Weaknesses":[{"Type":"Colorless","Value":"×2"}],"RetreatCost":["Colorless"],"ConvertedRetreatCost":1,"Set":{"ID":"pop1","Name":"POP Series 1","Series":"POP","PrintedTotal":17,"Total":17,"Legalities":{"unlimited":"Legal"},"PtcgoCode":"","ReleaseDate":"2004/09/01","UpdatedAt":"2018/03/04 10:35:00","Images":{"logo":"https://images.pokemontcg.io/pop1/logo.png","symbol":"https://images.pokemontcg.io/pop1/symbol.png"}},"Number":"3","Artist":"Katsura Tabata","Rarity":"Rare","NationalPokedexNumbers":[384],"Legalities":{"unlimited":"Legal"},"RegulationMark":"","Images":{"large":"https://images.pokemontcg.io/pop1/3_hires.png","small":"https://images.pokemontcg.io/pop1/3.png"},"CardMarket":{"URL":"https://prices.pokemontcg.io/cardmarket/pop1-3","UpdatedAt":"2022/03/18","Prices":{"AverageSellPrice":20.38,"LowPrice":7.5,"TrendPrice":11.51,"ReverseHoloTrend":11.95,"Avg1":29.9,"Avg7":16.59,"Avg30":16.11,"ReverseHoloAvg1":9,"ReverseHoloAvg7":23.17,"ReverseHoloAvg30":11.27}}}}
