{"data":{"ID":"swsh9-109","Name":"Garchomp","Supertype":"Pokémon","Subtypes":["Stage 2"],"HP":"160","Types":["Dragon"],"EvolvesFrom":"Gabite","Rules":null,"Attacks":[{"Name":"Dragonblade","Cost":["Water","Fighting"],"ConvertedEnergyCost":2,"Damage":"160","Text":"Discard the top 2 cards of your deck."}],"Weaknesses":null,"RetreatCost":["Colorless"],"ConvertedRetreatCost":1,"Set":{"ID":"swsh9","Name":"Brilliant Stars","Series":"Sword \u0026 Shield","PrintedTotal":172,"Total":186,"Legalities":{"expanded":"Legal","standard":"Legal","unlimited":"Legal"},"PtcgoCode":"BRS","ReleaseDate":"2022/02/25","UpdatedAt":"2022/02/23 09:45:00","Images":{"logo":"https://images.pokemontcg.io/swsh9/logo.png","symbol":"https://images.pokemontcg.io/swsh9/symbol.png"}},"Number":"109","Artist":"Nurikabe","Rarity":"Rare Holo","NationalPokedexNumbers":[445],"Legalities":{"expanded":"Legal","standard":"Legal","unlimited":"Legal"},"RegulationMark":"F","Images":{"large":"https://images.pokemontcg.io/swsh9/109_hires.png","small":"https://images.pokemontcg.io/swsh9/109.png"},"CardMarket":{"URL":"https://prices.pokemontcg.io/cardmarket/swsh9-109","UpdatedAt":"2022/03/24","Prices":{"AverageSellPrice":0.22,"LowPrice":0.02,"TrendPrice":0.13,"ReverseHoloTrend":0.43,"Avg1":0.08,"Avg7":0.18,"Avg30":0.22,"ReverseHoloAvg1":0.34,"ReverseHoloAvg7":0.43,"ReverseHoloAvg30":0.51}}}}
