{"data":{"ID":"xy8-60","Name":"Gengar","Supertype":"Pokémon","Subtypes":["Stage 2"],"HP":"130","Types":["Psychic"],"EvolvesFrom":"Haunter","Rules":null,"Attacks":[{"Name":"Sinister Fog","Cost":["Psychic"],"ConvertedEnergyCost":1,"Damage":"","Text":"Your opponent's Active Pokémon is now Poisoned. Put 1 damage counter on each of your opponent's Benched Pokémon."},{"Name":"Creep Show","Cost":["Psychic","Colorless"],"ConvertedEnergyCost":2,"Damage":"","Text":"If your opponent's Active Pokémon has 3 or more damage counters on it, that Pokémon is Knocked Out."}],"Weaknesses":[{"Type":"Darkness","Value":"×2"}],"RetreatCost":null,"ConvertedRetreatCost":0,"Set":{"ID":"xy8","Name":"BREAKthrough","Series":"XY","PrintedTotal":162,"Total":165,"Legalities":{"expanded":"Legal","unlimited":"Legal"},"PtcgoCode":"BKT","ReleaseDate":"2015/11/04","UpdatedAt":"2019/04/10 19:59:00","Images":{"logo":"https://images.pokemontcg.io/xy8/logo.png","symbol":"https://images.pokemontcg.io/xy8/symbol.png"}},"Number":"60","Artist":"Saya Tsuruta","Rarity":"Rare Holo","NationalPokedexNumbers":[94],"Legalities":{"expanded":"Legal","unlimited":"Legal"},"RegulationMark":"","Images":{"large":"https://images.pokemontcg.io/xy8/60_hires.png","small":"https://images.pokemontcg.io/xy8/60.png"},"CardMarket":{"URL":"https://prices.pokemontcg.io/cardmarket/xy8-60","UpdatedAt":"2022/03/14","Prices":{"AverageSellPrice":6.99,"LowPrice":3,"TrendPrice":5.85,"ReverseHoloTrend":11.48,"Avg1":3,"Avg7":5.18,"Avg30":5.51,"ReverseHoloAvg1":15,"ReverseHoloAvg7":9.89,"ReverseHoloAvg30":6.41}}}}
