{"data":{"ID":"xy8-164","Name":"Mewtwo-EX","Supertype":"Pokémon","Subtypes":["Basic","EX"],"HP":"170","Types":["Psychic"],"EvolvesFrom":"","Rules":["Pokémon-EX rule: When a Pokémon-EX has been Knocked Out, your opponent takes 2 Prize cards."],"Attacks":[{"Name":"Shatter Shot","Cost":["Psychic"],"ConvertedEnergyCost":1,"Damage":"30×","Text":"This attack does 30 damage times the amount of Psychic Energy attached to this Pokémon."},{"Name":"Damage Change","Cost":["Psychic","Psychic","Colorless"],"ConvertedEnergyCost":3,"Damage":"","Text":"Switch all damage counters on this Pokémon with those on your opponent's Active Pokémon."}],"Weaknesses":[{"Type":"Psychic","Value":"×2"}],"RetreatCost":["Colorless","Colorless"],"ConvertedRetreatCost":2,"Set":{"ID":"xy8","Name":"BREAKthrough","Series":"XY","PrintedTotal":162,"Total":165,"Legalities":{"expanded":"Legal","unlimited":"Legal"},"PtcgoCode":"BKT","ReleaseDate":"2015/11/04","UpdatedAt":"2019/04/10 19:59:00","Images":{"logo":"https://images.pokemontcg.io/xy8/logo.png","symbol":"https://images.pokemontcg.io/xy8/symbol.png"}},"Number":"164","Artist":"Mitsuhiro Arita","Rarity":"Rare Secret","NationalPokedexNumbers":[150],"Legalities":{"expanded":"Legal","unlimited":"Legal"},"RegulationMark":"","Images":{"large":"https://images.pokemontcg.io/xy8/164_hires.png","small":"https://images.pokemontcg.io/xy8/164.png"},"CardMarket":{"URL":"https://prices.pokemontcg.io/cardmarket/xy8-164","UpdatedAt":"2022/03/18","Prices":{"AverageSellPrice":69.99,"LowPrice":23.9,"TrendPrice":44.33,"ReverseHoloTrend":53.56,"Avg1":69.99,"Avg7":52.49,"Avg30":48.09,"ReverseHoloAvg1":39.99,"ReverseHoloAvg7":35.76,"ReverseHoloAvg30":31.06}}}}
